CHANGELOG.md
onebag/__init__.py
onebag/functions.py
onebag-0.1.3.dist-info/METADATA
onebag-0.1.3.dist-info/WHEEL
onebag-0.1.3.dist-info/RECORD
